Pruebas/REGS_SD/probador_regs.v
module probador(clk, rw, addr, data_in, data_out, ack, req, reset);

//Salidas y entradas	
	
  parameter data_witdh = 32;
  parameter addr_witdh = 5;
  parameter reg_witdh = 28;

   output clk;
   
   output rw;
   reg rw;
   
   output req;
   reg req;
   
   input ack;
   wire ack;
   
   output [addr_witdh-1: 0] addr;
   reg addr;
   
   output [data_witdh-1: 0] data_in;
   reg data_in;
   
   input [data_witdh-1: 0] data_out;
   wire data_out;
   
   output reset;
   reg reset = 1;

//Valores iniciales para las entradas 
	

//Cambio en las entradas según temporizador (en segundos)
	initial begin
		
	
		//Prueba ascendente
		$display("Inicia prueba");
		#1 reset = 0;
		addr = 5'b00000;
		req = 1'b1;
		rw = 1'b0; 
		data_in = 32'h00000001;
		#6 rw = 1'b1;
		#1 addr = 5'b00100;
		req = 1'b1;
		rw = 1'b0; 
		data_in = 32'h01010001;
		#6 rw = 1'b1;
		#1 req =1'b0;
		#1 addr = 5'b10110;
		req = 1'b1;
		rw = 1'b0; 
		data_in = 32'h11011010;
		#6 rw = 1'b1;
		#11 $finish;
	
	end
	
//Pulso de reloj cada segundo
	reg clk = 0;
	always #1 clk = !clk;

	
//contador c1 (Q, RCO, CLK, ENB, MODO, D, reset);

//Vista en pantalla
	initial
		$monitor("ack: %b", ack);
	
endmodule

Pruebas/REGS_SD/REG.v
module REG(clk, rw, addr, data_in, data_out, ack, req, reset);

  parameter data_witdh = 32;
  parameter addr_witdh = 5;
  parameter reg_witdh = 28;
   input clk;
   wire  clk;

   input rw;
   wire  rw;

   input req;
   wire  req;

   output ack;
   reg 	  ack;

   input [addr_witdh-1: 0] addr;
   wire 		   addr;

   input [data_witdh-1: 0] data_in;
   wire 		   data_in;

   output [data_witdh-1: 0] data_out;
   reg 			    data_out;

   input reset;
   wire reset;
   
   integer i;


   //0
   output [15: 0] 	    SDMA_System_Address_Low;
   wire [15: 0] 	    SDMA_System_Address_Low;
   output [15: 0] 	    SDMA_System_Address_High;
   wire [15: 0] 	    SDMA_System_Address_High;

   //1
   output [15: 0] 	    Block_Size;
   wire [15: 0] 	    Block_Size;
   output [15: 0] 	    Block_Count;
   wire [15: 0] 	    Block_Count;

   //2
   output [15: 0] 	    Argument0;
   wire [15: 0] 	    Argument0;
   output [15: 0] 	    Argument1;
   wire [15: 0] 	    Argument1;

   output [31:0] 	    Argument;
   wire [31:0] 		    Argument;
   assign        	    Argument[15:0] = Argument0;
   assign 		    Argument[31:16] = Argument1;

   //3
   output [15: 0] 	    Transfer_Mode;
   wire [15: 0] 	    Transfer_Mode;
   output [15: 0] 	    Command;
   wire [15: 0] 	    Command;
   wire [5:0] 		    cmd_index; //CMD
   assign cmd_index[5:0] = Command[13:8];

   //4-5-6-7
   output [15: 0] 	    Response0; //read only
   output [15: 0] 	    Response1;
   output [15: 0] 	    Response2;
   output [15: 0] 	    Response3;
   output [15: 0] 	    Response4;
   output [15: 0] 	    Response5;
   output [15: 0] 	    Response6;
   output [15: 0] 	    Response7;
   wire [15: 0] 	    Response0;
   wire [15: 0] 	    Response1;
   wire [15: 0] 	    Response2;
   wire [15: 0] 	    Response3;
   wire [15: 0] 	    Response4;
   wire [15: 0] 	    Response5;
   wire [15: 0] 	    Response6;
   wire [15: 0] 	    Response7;

   //8
   output [15: 0] 	    Buffer_Data_Port0;
   wire [15: 0] 	    Buffer_Data_Port0;
   output [15: 0] 	    Buffer_Data_Port1;
   wire [15: 0] 	    Buffer_Data_Port1;

   //9
   output [15: 0] 	    Present_State1; // read only
   wire [15: 0] 	    Present_State1;
   output [15: 0] 	    Present_State2;
   wire [15: 0] 	    Present_State2;

   //10
   output [7: 0] 	    Host_Control;
   output [7: 0] 	    Power_Control;
   wire [7: 0] 		    Host_Control;
   wire [7: 0] 		    Power_Control;
   output [7: 0] 	    Block_Gap_Control;
   output [7: 0] 	    Wakeup_Control;
   wire [7: 0] 		    Block_Gap_Control;
   wire [7: 0] 		    Wakeup_Control;

   //11
   output [15: 0] 	    Clock_Control;
   wire [15: 0] 	    Clock_Control;
   output [7: 0] 	    Timeout_Control;
   output [7: 0] 	    Software_Reset;
   wire [7: 0] 		    Timeout_Control;
   wire [7: 0] 		    Software_Reset;

   //12
   output [15: 0] 	    Normal_Interrupt_Status;
   wire [15: 0] 	    Normal_Interrupt_Status;
   output [15: 0] 	    Error_Interrupt_Status;
   wire [15: 0] 	    Error_Interrupt_Status;

   //13
   output [15: 0] 	    Normal_Interrupt_Status_Enable;
   wire [15: 0] 	    Normal_Interrupt_Status_Enable;
   output [15: 0] 	    Error_Interrupt_Status_Enable;
   wire [15: 0] 	    Error_Interrupt_Status_Enable;

   //14
   output [15: 0] 	    Normal_Interrupt_Signal_Enable;
   wire [15: 0] 	    Normal_Interrupt_Signal_Enable;
   output [15: 0] 	    Error_Interrupt_Signal_Enable;
   wire [15: 0] 	    Error_Interrupt_Signal_Enable;

   //15
   output [15: 0] 	    Auto_CMD12_Error_Status;
   wire [15: 0] 	    Auto_CMD12_Error_Status;
   //--

   //16
   output [15: 0] 	    Capabilities1; //*
   wire [15: 0] 	    Capabilities1; //*
   output [15: 0] 	    Capabilities2; //*
   wire [15: 0] 	    Capabilities2; //*

   //17
   output [15: 0] 	    Capabilities_Reserved_1; //*
   wire [15: 0] 	    Capabilities_Reserved_1; //*
   output [15: 0] 	    Capabilities_Reserved_2; //*
   wire [15: 0] 	    Capabilities_Reserved_2; //*

   //18
   output [15: 0] 	    Maximum_Current_Capabilities1; //*
   wire [15: 0] 	    Maximum_Current_Capabilities1; //*
   output [15: 0] 	    Maximum_Current_Capabilities2; //*
   wire [15: 0] 	    Maximum_Current_Capabilities2; //*

   //19
   output [15: 0] 	    Maximum_Current_Capabilities_Reserved_1; //*
   output [15: 0] 	    Maximum_Current_Capabilities_Reserved_2; //*
   wire [15: 0] 	    Maximum_Current_Capabilities_Reserved_1; //*
   wire [15: 0] 	    Maximum_Current_Capabilities_Reserved_2; //*

   //20
   output [15: 0] 	    Force_Event_for_Auto_CMD12_Error_Status;
   output [15: 0] 	    Force_Event_for_Error_Interrupt_Status;
   wire [15: 0] 	    Force_Event_for_Auto_CMD12_Error_Status;
   wire [15: 0] 	    Force_Event_for_Error_Interrupt_Status;

   //21
   output [7: 0] 	    ADMA_Error_Status;//*
   wire [7: 0] 		    ADMA_Error_Status;//*

   //22-23
   output [15: 0] 	    ADMA_System_Address_15;
   output [15: 0] 	    ADMA_System_Address_31;
   output [15: 0] 	    ADMA_System_Address_47;
   output [15: 0] 	    ADMA_System_Address_63;
   wire [15: 0] 	    ADMA_System_Address_15;
   wire [15: 0] 	    ADMA_System_Address_31;
   wire [15: 0] 	    ADMA_System_Address_47;
   wire [15: 0] 	    ADMA_System_Address_63;

   //27
   output [15: 0] 	    Host_Controller_Version;
   output [15: 0] 	    Slot_Interrupt_Status;
   wire [15: 0] 	    Host_Controller_Version;
   wire [15: 0] 	    Slot_Interrupt_Status;

   //24
   output [15:0] 	    Timeout_Reg;
   wire [15:0] 		    Timeout_Reg;

   output [15:0] 	    data;
   wire 		    writeRead;
   wire 		    multipleData;
   wire 		    timeout_enable;
   
   //25
    input cmd_complete;
	wire cmd_complete;
    input cmd_index_error;
	wire cmd_index_error;
    always @(cmd_complete)
	regs[5'b11001][0] <= cmd_complete;
	
	always @(cmd_index_error)
	regs[5'b11001][1] <= cmd_index_error;
	

   reg [data_witdh-1: 0]    regs [0: reg_witdh-1];

   assign SDMA_System_Address_Low[15:0] = regs[5'b00000][15:0];
   assign SDMA_System_Address_High[15:0] = regs[5'b00000][31:16];

   assign Block_Size[15:0] = regs[5'b00001][15:0];
   assign Block_Count[15:0] = regs[5'b00001][31:16];
   wire [3:0] 		    blockCount; //DATA
   assign blockCount = Block_Count[3:0];

   assign Argument0[15:0] = regs[ 5'b00010][15: 0];
   assign Argument1[15:0] = regs[ 5'b00010][31: 16];

   assign Transfer_Mode[15:0] = regs[5'b00011];
   assign Command[15:0] = regs[5'b00011][31: 16];

   assign Response0[15:0] = regs[5'b00100][15:0];
   assign Response1[15:0] = regs[5'b00100][31: 16];

   assign Response2[15:0] = regs[5'b00101][15:0];
   assign Response3[15:0] = regs[5'b00101][31: 16];

   assign Response4[15:0] = regs[5'b00110][15:0];
   assign Response5[15:0] = regs[5'b00110][31: 16];

   assign Response6[15:0] = regs[5'b00111][15:0];
   assign Response7[15:0] = regs[5'b00111][31: 16];

   assign Buffer_Data_Port0[15:0] = regs[5'b01000][15:0];
   assign Buffer_Data_Port1[15:0] = regs[5'b01000][31: 16];

   assign Present_State1[15:0] = regs[5'b01001][15:0];
   assign Present_State2[15:0] = regs[5'b01001][31: 16];

   assign Host_Control[7:0] = regs[5'b01010][7:0];
   assign Power_Control[7:0] = regs[5'b01010][15:8];
   assign Block_Gap_Control[7:0] = regs[5'b01010][23:16];
   assign Wakeup_Control[7:0] = regs[5'b01010][31:24];

   assign Clock_Control[15:0] = regs[5'b01011][15:0];
   assign Timeout_Control[7:0] = regs[5'b01011][23:16];
   assign Software_Reset[7:0] = regs[5'b01011][31:24];

   assign Normal_Interrupt_Status[15:0] = regs[5'b01100][15:0];
   assign Error_Interrupt_Status[15:0] = regs[5'b01100][31: 16];

   assign Normal_Interrupt_Status_Enable[15:0] = regs[5'b01101][15:0];
   assign Error_Interrupt_Status_Enable[15:0] = regs[5'b01101][31: 16];

   assign Normal_Interrupt_Signal_Enable[15:0] = regs[5'b01110][15:0];
   assign Error_Interrupt_Signal_Enable[15:0] = regs[5'b01110][31: 16];

   assign Auto_CMD12_Error_Status[15:0] = regs[5'b01111][15:0];
   //assign 0 = [31: 16] regs[addr];

   assign Capabilities1[15:0] = regs[5'b10000][15:0];
   assign Capabilities2[15:0] = regs[5'b10000][31: 16];

   assign Capabilities_Reserved_1[15:0] = regs[5'b10001][15:0];
   assign Capabilities_Reserved_2[15:0] = regs[5'b10001][31: 16];

   assign Maximum_Current_Capabilities1[15:0] = regs[5'b10010][15:0];
   assign Maximum_Current_Capabilities2[15:0] = regs[5'b10010][31: 16];

   assign Maximum_Current_Capabilities_Reserved_1[15:0] = regs[5'b10011][15:0];
   assign Maximum_Current_Capabilities_Reserved_2[15:0] = regs[5'b10011][31: 16];

   assign Force_Event_for_Auto_CMD12_Error_Status[15:0] = regs[5'b10100][15:0];
   assign Force_Event_for_Error_Interrupt_Status[15:0] = regs[5'b10100][31: 16];

   assign ADMA_Error_Status[7:0] = regs[5'b10101][7:0];


   assign ADMA_System_Address_15[15:0] = regs[5'b10110][15:0];
   assign ADMA_System_Address_31[15:0] = regs[5'b10110][31: 16];

   assign ADMA_System_Address_47[15:0] = regs[5'b10111][15:0];
   assign ADMA_System_Address_63[15:0] = regs[5'b10111][31: 16];

   assign Slot_Interrupt_Status[15: 0] = regs[5'b10011][15: 0];
   assign Host_Controller_Version[15: 0] = regs[5'b10011][31: 16];

   assign Timeout_Reg[15: 0] = regs[5'b11000][15: 0];
   assign data[15: 0] = regs[5'b11000][31: 16];


  // assign timeout_Reg[14:0] = Timeout[14:0]; //DATA
   assign timeout_enable = data[0];
   assign writeRead = data[1];
   assign multipleData = data[2];

   assign cmd_complete = regs[5'b11001][0];
   assign cmd_complete = regs[5'b11001][0];


   // Lectura y escritura desde CPU (se estan leyendo y escribiendo 32)
   always @(posedge clk) begin
     if(req == 1'b1) begin
	 if(rw == 1'b1) begin //lectura
	    data_out <= regs[addr];
	    ack <= 1'b1;
	 end
	 else begin
	    regs[addr] <= data_in;
	    ack <= 1'b1;
	 end
      end
      else begin
	 data_out <= data_out;
	 ack <= 1'b0;
      end
   end
   
   always @(reset) begin
	if(reset == 1'b1) begin
		for (i=0; i<28; i=i+1) begin
			regs[i] = 0;
		end
	end 
	end 
		

endmodule

Pruebas/REGS_SD/probador_tb.v
`include "REG.v"
`include "probador_regs.v"
module testbench;

	parameter data_witdh = 32;
	parameter addr_witdh = 5;
	parameter reg_witdh = 28;
   
   
   wire clk;
   
   wire rw;
   
   wire req;
   
   wire ack;
   
   wire [addr_witdh-1: 0]addr;
   
   wire [data_witdh-1: 0]data_in;

   wire [data_witdh-1: 0]data_out;
   
   wire reset;
   
   initial begin
	$dumpfile("registers.vcd");
	$dumpvars(0, testbench);
	end

REG b1 (clk, rw, addr, data_in, data_out, ack, req, reset);
probador p1 (clk, rw, addr, data_in, data_out, ack, req, reset);

endmodule

//iverilog -o reg.vvp probador_tb.v

Pruebas/REGS_SD/registers.vcd
$date
	Thu Dec 08 09:30:11 2016
$end
$version
	Icarus Verilog
$end
$timescale
	1s
$end
$scope module testbench $end
$var wire 1 ! ack $end
$var wire 5 " addr [4:0] $end
$var wire 1 # clk $end
$var wire 32 $ data_in [31:0] $end
$var wire 32 % data_out [31:0] $end
$var wire 1 & req $end
$var wire 1 ' reset $end
$var wire 1 ( rw $end
$scope module b1 $end
$var wire 8 ) ADMA_Error_Status [7:0] $end
$var wire 16 * ADMA_System_Address_15 [15:0] $end
$var wire 16 + ADMA_System_Address_31 [15:0] $end
$var wire 16 , ADMA_System_Address_47 [15:0] $end
$var wire 16 - ADMA_System_Address_63 [15:0] $end
$var wire 32 . Argument [31:0] $end
$var wire 16 / Argument0 [15:0] $end
$var wire 16 0 Argument1 [15:0] $end
$var wire 16 1 Auto_CMD12_Error_Status [15:0] $end
$var wire 16 2 Block_Count [15:0] $end
$var wire 8 3 Block_Gap_Control [7:0] $end
$var wire 16 4 Block_Size [15:0] $end
$var wire 16 5 Buffer_Data_Port0 [15:0] $end
$var wire 16 6 Buffer_Data_Port1 [15:0] $end
$var wire 16 7 Capabilities1 [15:0] $end
$var wire 16 8 Capabilities2 [15:0] $end
$var wire 16 9 Capabilities_Reserved_1 [15:0] $end
$var wire 16 : Capabilities_Reserved_2 [15:0] $end
$var wire 16 ; Clock_Control [15:0] $end
$var wire 16 < Command [15:0] $end
$var wire 16 = Error_Interrupt_Signal_Enable [15:0] $end
$var wire 16 > Error_Interrupt_Status [15:0] $end
$var wire 16 ? Error_Interrupt_Status_Enable [15:0] $end
$var wire 16 @ Force_Event_for_Auto_CMD12_Error_Status [15:0] $end
$var wire 16 A Force_Event_for_Error_Interrupt_Status [15:0] $end
$var wire 8 B Host_Control [7:0] $end
$var wire 16 C Host_Controller_Version [15:0] $end
$var wire 16 D Maximum_Current_Capabilities1 [15:0] $end
$var wire 16 E Maximum_Current_Capabilities2 [15:0] $end
$var wire 16 F Maximum_Current_Capabilities_Reserved_1 [15:0] $end
$var wire 16 G Maximum_Current_Capabilities_Reserved_2 [15:0] $end
$var wire 16 H Normal_Interrupt_Signal_Enable [15:0] $end
$var wire 16 I Normal_Interrupt_Status [15:0] $end
$var wire 16 J Normal_Interrupt_Status_Enable [15:0] $end
$var wire 8 K Power_Control [7:0] $end
$var wire 16 L Present_State1 [15:0] $end
$var wire 16 M Present_State2 [15:0] $end
$var wire 16 N Response0 [15:0] $end
$var wire 16 O Response1 [15:0] $end
$var wire 16 P Response2 [15:0] $end
$var wire 16 Q Response3 [15:0] $end
$var wire 16 R Response4 [15:0] $end
$var wire 16 S Response5 [15:0] $end
$var wire 16 T Response6 [15:0] $end
$var wire 16 U Response7 [15:0] $end
$var wire 16 V SDMA_System_Address_High [15:0] $end
$var wire 16 W SDMA_System_Address_Low [15:0] $end
$var wire 16 X Slot_Interrupt_Status [15:0] $end
$var wire 8 Y Software_Reset [7:0] $end
$var wire 8 Z Timeout_Control [7:0] $end
$var wire 16 [ Timeout_Reg [15:0] $end
$var wire 16 \ Transfer_Mode [15:0] $end
$var wire 8 ] Wakeup_Control [7:0] $end
$var wire 5 ^ addr [4:0] $end
$var wire 4 _ blockCount [3:0] $end
$var wire 1 # clk $end
$var wire 1 ` cmd_complete $end
$var wire 6 a cmd_index [5:0] $end
$var wire 1 b cmd_index_error $end
$var wire 16 c data [15:0] $end
$var wire 32 d data_in [31:0] $end
$var wire 1 e multipleData $end
$var wire 1 & req $end
$var wire 1 ' reset $end
$var wire 1 ( rw $end
$var wire 1 f timeout_enable $end
$var wire 1 g writeRead $end
$var reg 1 h ack $end
$var reg 32 i data_out [31:0] $end
$var integer 32 j i [31:0] $end
$upscope $end
$scope module p1 $end
$var wire 1 ! ack $end
$var wire 32 k data_out [31:0] $end
$var reg 5 l addr [4:0] $end
$var reg 1 m clk $end
$var reg 32 n data_in [31:0] $end
$var reg 1 o req $end
$var reg 1 p reset $end
$var reg 1 q rw $end
$upscope $end
$upscope $end
$enddefinitions $end
#0
$dumpvars
xq
1p
xo
bx n
0m
bx l
bx k
b11100 j
bx i
xh
0g
0f
0e
bx d
b0 c
zb
b0 a
0`
b0 _
bx ^
b0 ]
b0 \
b0 [
b0 Z
b0 Y
b0 X
b0 W
b0 V
b0 U
b0 T
b0 S
b0 R
b0 Q
b0 P
b0 O
b0 N
b0 M
b0 L
b0 K
b0 J
b0 I
b0 H
b0 G
b0 F
b0 E
b0 D
b0 C
b0 B
b0 A
b0 @
b0 ?
b0 >
b0 =
b0 <
b0 ;
b0 :
b0 9
b0 8
b0 7
b0 6
b0 5
b0 4
b0 3
b0 2
b0 1
b0 0
b0 /
b0 .
b0 -
b0 ,
b0 +
b0 *
b0 )
x(
1'
x&
bx %
bx $
0#
bx "
x!
$end
#1
b1 W
1h
1!
1m
1#
b1 n
b1 $
b1 d
0q
0(
1o
1&
b0 l
b0 "
b0 ^
0p
0'
#2
0m
0#
#3
1m
1#
#4
0m
0#
#5
1m
1#
#6
0m
0#
#7
b1 i
b1 %
b1 k
1m
1#
1q
1(
#8
0m
0#
b1000000010000000000000001 n
b1000000010000000000000001 $
b1000000010000000000000001 d
0q
0(
b100 l
b100 "
b100 ^
#9
b1 N
b100000001 O
1m
1#
#10
0m
0#
#11
1m
1#
#12
0m
0#
#13
1m
1#
#14
0m
0#
1q
1(
#15
0h
0!
1m
1#
0o
0&
#16
0m
0#
b10001000000010001000000010000 n
b10001000000010001000000010000 $
b10001000000010001000000010000 d
0q
0(
1o
1&
b10110 l
b10110 "
b10110 ^
#17
b1000000010000 *
b1000100000001 +
1h
1!
1m
1#
#18
0m
0#
#19
1m
1#
#20
0m
0#
#21
1m
1#
#22
0m
0#
1q
1(
#23
b10001000000010001000000010000 i
b10001000000010001000000010000 %
b10001000000010001000000010000 k
1m
1#
